pennylane_lightning_kokkos-0.44.0.dist-info/RECORD
pennylane_lightning_kokkos-0.44.0.dist-info/WHEEL
pennylane_lightning_kokkos-0.44.0.dist-info/entry_points.txt
pennylane_lightning_kokkos-0.44.0.dist-info/top_level.txt
pennylane_lightning_kokkos-0.44.0.dist-info/METADATA
pennylane_lightning_kokkos-0.44.0.dist-info/licenses/LICENSE
pennylane_lightning/liblightning_kokkos_catalyst.dylib
pennylane_lightning/lightning_kokkos_ops.cpython-313-darwin.so
pennylane_lightning/lightning_kokkos/_state_vector.py
pennylane_lightning/lightning_kokkos/_adjoint_jacobian.py
pennylane_lightning/lightning_kokkos/_measurements.py
pennylane_lightning/lightning_kokkos/lightning_kokkos.py
pennylane_lightning/lightning_kokkos/__init__.py
pennylane_lightning/lightning_kokkos/lightning_kokkos.toml
