Metadata-Version: 2.4
Name: pennylane_lightning_kokkos
Version: 0.44.0
Summary: PennyLane-Lightning plugin
Maintainer-email: "Xanadu Quantum Technologies Inc." <software@xanadu.ai>
License-Expression: Apache-2.0
Project-URL: Homepage, https://github.com/PennyLaneAI/pennylane-lightning
Classifier: Development Status :: 4 - Beta
Classifier: Environment :: Console
Classifier: Intended Audience :: Science/Research
Classifier: Natural Language :: English
Classifier: Operating System :: MacOS :: MacOS X
Classifier: Operating System :: POSIX
Classifier: Operating System :: POSIX :: Linux
Classifier: Programming Language :: Python
Classifier: Programming Language :: Python :: 3
Classifier: Programming Language :: Python :: 3 :: Only
Classifier: Programming Language :: Python :: 3.11
Classifier: Programming Language :: Python :: 3.12
Classifier: Programming Language :: Python :: 3.13
Classifier: Programming Language :: Python :: 3.14
Classifier: Topic :: Scientific/Engineering :: Physics
Requires-Python: >=3.11
License-File: LICENSE
Requires-Dist: pennylane>=0.42
Requires-Dist: scipy-openblas32>=0.3.26
Requires-Dist: pennylane_lightning==0.44.0
Provides-Extra: kokkos
Requires-Dist: pennylane-lightning-kokkos; extra == "kokkos"
Provides-Extra: amdgpu
Requires-Dist: pennylane-lightning-amdgpu; extra == "amdgpu"
Provides-Extra: gpu
Requires-Dist: pennylane-lightning-gpu; extra == "gpu"
Provides-Extra: tensor
Requires-Dist: pennylane-lightning-tensor; extra == "tensor"
Dynamic: license-file
